LOLZTEAM/Client/Antipublic.py
LOLZTEAM/Client/Base/Constants.py
LOLZTEAM/Client/Base/Core.py
LOLZTEAM/Client/Base/Exceptions.py
LOLZTEAM/Client/Base/Wrappers.py
LOLZTEAM/Client/Base/__init__.py
LOLZTEAM/Client/Forum.py
LOLZTEAM/Client/Market.py
LOLZTEAM/Client/__init__.py
LOLZTEAM/__init__.py
lolzteam-2.0.18.dist-info/WHEEL
lolzteam-2.0.18.dist-info/METADATA
lolzteam-2.0.18.dist-info/RECORD
