Metadata-Version: 2.4
Name: lolzteam
Version: 2.0.18
Summary: Python API Client for https://lolz.live/ & https://lzt.market/ & https://antipublic.one/
Keywords: LZT,LOLZ,LOLZTEAM,ZELENKA,API,Client,Market,Forum,Antipublic
Author: AS7RID
Author-email: AS7RID <lolzteam@furrygaysex.anonaddy.com>
License-Expression: MIT
Requires-Dist: httpx[socks]
Requires-Python: >=3.9
Project-URL: homepage, https://lolz.live/threads/5523020/
Project-URL: repository, https://github.com/AS7RIDENIED/LOLZTEAM
Project-URL: documentation, https://github.com/AS7RIDENIED/LOLZTEAM/tree/main/Documentation
Project-URL: Bug Tracker, https://github.com/AS7RIDENIED/LOLZTEAM/issues
